md_tangle/__init__.py
md_tangle/__main__.py
md_tangle/main.py
md_tangle/save.py
md_tangle/tangle.py
md_tangle-1.4.4.dist-info/LICENSE
md_tangle-1.4.4.dist-info/METADATA
md_tangle-1.4.4.dist-info/WHEEL
md_tangle-1.4.4.dist-info/entry_points.txt
md_tangle-1.4.4.dist-info/top_level.txt
md_tangle-1.4.4.dist-info/RECORD
