Metadata-Version: 2.1
Name: md-tangle
Version: 1.4.4
Summary: Generates ('tangles') source code from Markdown documents
Home-page: https://github.com/joakimmj/md-tangle
Author: Joakim Myrvoll Johansen
Author-email: joakimmyrvoll@gmail.com
License: MIT
Keywords: markdown,tangle,literate programming
Platform: any
Classifier: Environment :: Console
Classifier: License :: OSI Approved :: MIT License
Classifier: Operating System :: OS Independent
Classifier: Natural Language :: English
Classifier: Topic :: Text Processing :: Markup
Classifier: Programming Language :: Python
Classifier: Programming Language :: Python :: 2
Classifier: Programming Language :: Python :: 3
License-File: LICENSE
